keras_cv/__init__.py
keras_cv/bounding_box/__init__.py
keras_cv/callbacks/__init__.py
keras_cv/core/__init__.py
keras_cv/datasets/__init__.py
keras_cv/datasets/imagenet/__init__.py
keras_cv/datasets/pascal_voc/__init__.py
keras_cv/datasets/pascal_voc/segmentation/__init__.py
keras_cv/datasets/waymo/__init__.py
keras_cv/keypoint/__init__.py
keras_cv/layers/__init__.py
keras_cv/losses/__init__.py
keras_cv/metrics/__init__.py
keras_cv/models/__init__.py
keras_cv/models/classification/__init__.py
keras_cv/models/object_detection/__init__.py
keras_cv/models/retinanet/__init__.py
keras_cv/models/segmentation/__init__.py
keras_cv/models/stable_diffusion/__init__.py
keras_cv/models/yolov8/__init__.py
keras_cv/src/__init__.py
keras_cv/src/api_export.py
keras_cv/src/conftest.py
keras_cv/src/version_check.py
keras_cv/src/version_utils.py
keras_cv/src/backend/__init__.py
keras_cv/src/backend/config.py
keras_cv/src/backend/keras.py
keras_cv/src/backend/ops.py
keras_cv/src/backend/random.py
keras_cv/src/backend/scope.py
keras_cv/src/backend/tf_ops.py
keras_cv/src/bounding_box/__init__.py
keras_cv/src/bounding_box/converters.py
keras_cv/src/bounding_box/ensure_tensor.py
keras_cv/src/bounding_box/formats.py
keras_cv/src/bounding_box/iou.py
keras_cv/src/bounding_box/mask_invalid_detections.py
keras_cv/src/bounding_box/to_dense.py
keras_cv/src/bounding_box/to_ragged.py
keras_cv/src/bounding_box/utils.py
keras_cv/src/bounding_box/validate_format.py
keras_cv/src/bounding_box_3d/__init__.py
keras_cv/src/bounding_box_3d/formats.py
keras_cv/src/callbacks/__init__.py
keras_cv/src/callbacks/pycoco_callback.py
keras_cv/src/callbacks/waymo_evaluation_callback.py
keras_cv/src/core/__init__.py
keras_cv/src/core/factor_sampler/__init__.py
keras_cv/src/core/factor_sampler/constant_factor_sampler.py
keras_cv/src/core/factor_sampler/factor_sampler.py
keras_cv/src/core/factor_sampler/normal_factor_sampler.py
keras_cv/src/core/factor_sampler/uniform_factor_sampler.py
keras_cv-0.8.2.dist-info/METADATA
keras_cv-0.8.2.dist-info/WHEEL
keras_cv-0.8.2.dist-info/top_level.txt
keras_cv-0.8.2.dist-info/RECORD
