Metadata-Version: 2.1
Name: keras-cv
Version: 0.8.2
Summary: Industry-strength computer Vision extensions for Keras.
Home-page: https://github.com/keras-team/keras-cv
Author: Keras team
Author-email: keras-cv@google.com
License: Apache License 2.0
Classifier: Development Status :: 3 - Alpha
Classifier: Programming Language :: Python :: 3
Classifier: Programming Language :: Python :: 3.9
Classifier: Programming Language :: Python :: 3.10
Classifier: Programming Language :: Python :: 3.11
Classifier: Programming Language :: Python :: 3 :: Only
Classifier: Operating System :: Unix
Classifier: Operating System :: Microsoft :: Windows
Classifier: Operating System :: MacOS
Classifier: Intended Audience :: Science/Research
Classifier: Topic :: Scientific/Engineering
Classifier: Topic :: Software Development
Requires-Python: >=3.9
Requires-Dist: packaging
Requires-Dist: absl-py
Requires-Dist: regex
Requires-Dist: tensorflow-datasets
Requires-Dist: keras-core
Requires-Dist: kagglehub
Provides-Extra: examples
Requires-Dist: tensorflow-datasets ; extra == 'examples'
Requires-Dist: matplotlib ; extra == 'examples'
Provides-Extra: tests
Requires-Dist: flake8 ; extra == 'tests'
Requires-Dist: isort ; extra == 'tests'
Requires-Dist: black[jupyter] ; extra == 'tests'
Requires-Dist: pytest ; extra == 'tests'
Requires-Dist: pycocotools ; extra == 'tests'
